odoo/addons/sale_report_delivered/README.rst
odoo/addons/sale_report_delivered/__init__.py
odoo/addons/sale_report_delivered/__manifest__.py
odoo/addons/sale_report_delivered/i18n/es.po
odoo/addons/sale_report_delivered/i18n/it.po
odoo/addons/sale_report_delivered/i18n/sale_report_delivered.pot
odoo/addons/sale_report_delivered/readme/CONTRIBUTORS.rst
odoo/addons/sale_report_delivered/readme/DESCRIPTION.rst
odoo/addons/sale_report_delivered/readme/USAGE.rst
odoo/addons/sale_report_delivered/reports/__init__.py
odoo/addons/sale_report_delivered/reports/sale_report.py
odoo/addons/sale_report_delivered/security/ir.model.access.csv
odoo/addons/sale_report_delivered/static/description/icon.png
odoo/addons/sale_report_delivered/static/description/index.html
odoo/addons/sale_report_delivered/tests/__init__.py
odoo/addons/sale_report_delivered/tests/test_sale_report_delivered.py
odoo/addons/sale_report_delivered/views/sale_report_delivered_views.xml
odoo14_addon_sale_report_delivered-14.0.1.0.1.dev6.dist-info/METADATA
odoo14_addon_sale_report_delivered-14.0.1.0.1.dev6.dist-info/WHEEL
odoo14_addon_sale_report_delivered-14.0.1.0.1.dev6.dist-info/top_level.txt
odoo14_addon_sale_report_delivered-14.0.1.0.1.dev6.dist-info/RECORD
